Evpc/__init__.py
Evpc/py.typed
Evpc/_jsii/__init__.py
Evpc/_jsii/raindancers-network@1.29.3.jsii.tgz
Evpc/apilambda/__init__.py
Evpc/cloudwan/__init__.py
Evpc/crowdstrike/__init__.py
Evpc/delay/__init__.py
Evpc/dns/__init__.py
Evpc/ec2/__init__.py
Evpc/endpoints/__init__.py
Evpc/firewall/__init__.py
Evpc/glue/__init__.py
Evpc/ipam/__init__.py
Evpc/lakeformation/__init__.py
Evpc/network/__init__.py
Evpc/redshift/__init__.py
Evpc/regions/__init__.py
Evpc/ssm/__init__.py
Evpc/sso/__init__.py
raindancers_network.raindancers_cdk-1.29.3.dist-info/LICENSE
raindancers_network.raindancers_cdk-1.29.3.dist-info/METADATA
raindancers_network.raindancers_cdk-1.29.3.dist-info/WHEEL
raindancers_network.raindancers_cdk-1.29.3.dist-info/top_level.txt
raindancers_network.raindancers_cdk-1.29.3.dist-info/RECORD
